persinator/__init__.py
persinator/main.py
persinator/person_generator.py
persinator/data/MOCK_DATA.json
Persinator-0.1.0.dist-info/LICENSE
Persinator-0.1.0.dist-info/METADATA
Persinator-0.1.0.dist-info/WHEEL
Persinator-0.1.0.dist-info/top_level.txt
Persinator-0.1.0.dist-info/RECORD
